{"aid": "igkq1f297bw1v9", "error": null, "result": {"default_anonymity": "no", "status": "active", "i_edits": [], "q_edits": [], "bookmarked": 4, "request_instructor": 0, "history": [{"uid": "i6roqnlkmtw", "anon": "no", "created": "2015-05-26T14:53:30Z", "content": "<p>在ucore中实现的信号量是可以保证顺序的&#xff0c;即A&#xff0c;B两个进程先后通过P操作等待在某个信号量上&#xff0c;之后如果有两次V操作的话一定是A先执行&#xff0c;B再执行。</p>\n<p>但是我查到在一些其他系统中信号量似乎并不能保证顺序性这一点。</p>\n<p></p>\n<p>所以如果明天考试中遇到信号量相关的问题的话&#xff0c;我们可否假设信号量就是像ucore中实现的这样能够保证顺序的呢&#xff1f;还是必须要通过其他方式自己维护顺序&#xff1f;</p>", "subject": "信号量是否保证顺序&#xff1f;"}], "s_edits": [], "is_bookmarked": false, "tag_good_arr": [], "request_instructor_me": false, "my_favorite": false, "t": 1446636530817, "children": [{"is_tag_endorse": false, "created": "2015-05-26T14:58:15Z", "id": "ia5g6q2u2hj1kx", "tag_endorse": [], "folders": [], "history": [{"uid": "i6rgda76fc66q4", "anon": "no", "created": "2015-05-26T14:58:15Z", "content": "<p>lz大神果然慧眼独具&#xff0c;问题如此犀利。</p>\n<p></p>\n<p>同问啊。</p>", "subject": ""}], "config": {}, "data": {"embed_links": []}, "bucket_order": 2, "bucket_name": "Today", "tag_endorse_arr": [], "children": [], "type": "s_answer"}, {"is_tag_endorse": false, "created": "2015-05-26T15:05:38Z", "id": "ia5gg7idymv3hj", "tag_endorse": [], "folders": [], "history": [{"uid": "hdjonbiyfs62ie", "anon": "no", "created": "2015-05-26T15:05:38Z", "content": "<p>你可以假定ucore的信号量是可以保证顺序的。</p>", "subject": ""}], "config": {}, "data": {"embed_links": []}, "bucket_order": 2, "bucket_name": "Today", "tag_endorse_arr": [], "children": [], "type": "i_answer"}], "type": "question", "unique_views": 64, "created": "2015-05-26T14:53:30Z", "id": "ia5g0lvjnlg2qn", "no_answer": 0, "nr": 460, "data": {"embed_links": []}, "upvote_ids": [], "is_tag_good": false, "config": {}, "folders": ["lab7"], "bucket_order": 2, "change_log": [{"uid": "i6roqnlkmtw", "when": "2015-05-26T14:53:30Z", "data": "ia5g0lvmlcm2qo", "anon": "no", "type": "create"}, {"uid": "i6rgda76fc66q4", "when": "2015-05-26T14:58:15Z", "data": "ia5g6q2z2ub1ky", "to": "ia5g0lvjnlg2qn", "anon": "no", "type": "s_answer"}, {"uid": "hdjonbiyfs62ie", "when": "2015-05-26T15:05:38Z", "data": "ia5gg7ifkh73hk", "to": "ia5g0lvjnlg2qn", "anon": "no", "type": "i_answer"}], "bucket_name": "Today", "tags": ["lab7", "student"], "no_answer_followup": 0, "num_favorites": 0, "tag_good": []}}