{"aid": "iajhhkiuxq05va", "result": {"tag_good_arr": [], "request_instructor": 0, "change_log": [{"type": "create", "anon": "no", "when": "2015-06-03T06:15:07Z", "uid": "hdjonbiyfs62ie", "data": "iagd0sag701f2"}], "is_bookmarked": false, "data": {"embed_links": []}, "bookmarked": 1, "status": "active", "s_edits": [], "history": [{"created": "2015-06-03T06:15:07Z", "subject": "MOOC对清华大学学生的影响", "anon": "no", "uid": "hdjonbiyfs62ie", "content": "<p>各位同学&#xff0c;大家好&#xff01;</p>\n<p></p>\n<p>为了确定后续的操作系统课的教学安排。请愿意分享自己对这学期操作系统课观点的同学6月7号前回答下面链接处的调查卷。谢谢&#xff01;</p>\n<p></p>\n<p><a href=\"http://www.sojump.com/jq/5159304.aspx\">http://www.sojump.com/jq/5159304.aspx</a></p>\n<p></p>"}], "id": "iagd0saepsvf1", "unique_views": 27, "request_instructor_me": false, "bucket_order": 2, "upvote_ids": [], "config": {"bypass_email": 1, "feed_groups": "清华学生_i5j09fnsl7k5x0"}, "my_favorite": false, "created": "2015-06-03T06:15:07Z", "default_anonymity": "no", "bucket_name": "Today", "type": "note", "children": [], "i_edits": [], "tag_good": [], "nr": 467, "num_favorites": 0, "no_answer_followup": 0, "is_tag_good": false, "t": 1433501007654, "folders": ["课堂问答", "通知"], "q_edits": [], "tags": ["instructor-note", "课堂问答", "通知"]}, "error": null}