{"aid": "ip9w3hj9xvx5xy", "result": {"folders": ["课堂问答"], "unique_views": 135, "request_instructor_me": false, "change_log": [{"data": "in5aytjer7v3ay", "anon": "no", "when": "2016-04-18T01:08:19Z", "uid": "hcrrjuyequh4bt", "type": "create"}, {"data": "in5b45qwrql227", "anon": "no", "when": "2016-04-18T01:12:28Z", "uid": "hcrrjuyequh4bt", "type": "update"}, {"data": "in5b4p7lsbz4ok", "anon": "no", "when": "2016-04-18T01:12:53Z", "uid": "hcrrjuyequh4bt", "type": "update"}, {"to": "in5aytjcakh3ax", "anon": "no", "when": "2016-04-18T01:24:42Z", "uid": "i0b2fq3ezjw50r", "type": "followup"}, {"to": "in5aytjcakh3ax", "anon": "no", "when": "2016-04-18T01:28:19Z", "uid": "il7co2fpfTV", "type": "followup"}, {"to": "in5aytjcakh3ax", "anon": "no", "when": "2016-04-18T01:34:26Z", "uid": "i0ckv5q1y0g3e3", "type": "followup"}, {"to": "in5aytjcakh3ax", "anon": "no", "when": "2016-04-18T01:37:18Z", "uid": "i0cbq1nfv1m496", "type": "followup"}, {"to": "in5aytjcakh3ax", "anon": "no", "when": "2016-04-18T01:38:17Z", "uid": "i0byevowhoc2ya", "type": "followup"}, {"to": "in5aytjcakh3ax", "anon": "no", "when": "2016-04-18T01:41:18Z", "uid": "i0eqj2z1h2y55", "type": "followup"}, {"to": "in5aytjcakh3ax", "anon": "no", "when": "2016-04-18T01:46:43Z", "uid": "i0f3rp5o38h4mk", "type": "followup"}, {"to": "in5aytjcakh3ax", "anon": "no", "when": "2016-04-18T01:55:46Z", "uid": "ikwla6afpqb", "type": "followup"}, {"to": "in5aytjcakh3ax", "anon": "no", "when": "2016-04-18T02:01:08Z", "uid": "i0f97hpgaug3eu", "type": "followup"}, {"to": "in5aytjcakh3ax", "anon": "no", "when": "2016-04-18T02:02:26Z", "uid": "i0d7xnweuzw2k2", "type": "followup"}, {"to": "in5aytjcakh3ax", "anon": "no", "when": "2016-04-18T02:02:44Z", "uid": "i6swz3atggR", "type": "followup"}, {"to": "in5aytjcakh3ax", "anon": "no", "when": "2016-04-18T02:18:47Z", "uid": "i0b0ihyxqrc2ej", "type": "feedback"}, {"to": "in5aytjcakh3ax", "anon": "no", "when": "2016-04-18T02:21:29Z", "uid": "i0er21z2bhp4dk", "type": "followup"}, {"to": "in5aytjcakh3ax", "anon": "no", "when": "2016-04-18T02:24:44Z", "uid": "ikvcvmupe4x7i1", "type": "feedback"}, {"to": "in5aytjcakh3ax", "anon": "no", "when": "2016-04-18T02:32:00Z", "uid": "i0et95bli7r7ky", "type": "followup"}, {"to": "in5aytjcakh3ax", "anon": "no", "when": "2016-04-18T02:32:30Z", "uid": "i0et95bli7r7ky", "type": "feedback"}, {"to": "in5aytjcakh3ax", "anon": "no", "when": "2016-04-18T02:36:04Z", "uid": "ie7xy6atuuc1re", "type": "followup"}, {"to": "in5aytjcakh3ax", "anon": "no", "when": "2016-04-18T02:38:48Z", "uid": "i81jxkfelf72a9", "type": "followup"}, {"to": "in5aytjcakh3ax", "anon": "no", "when": "2016-04-18T03:02:02Z", "uid": "i0anp25rzjk2wt", "type": "followup"}, {"to": "in5aytjcakh3ax", "anon": "no", "when": "2016-04-18T03:32:37Z", "uid": "ikvcvnm9rrk7is", "type": "feedback"}, {"to": "in5aytjcakh3ax", "anon": "no", "when": "2016-04-18T04:01:23Z", "uid": "i0f453lqmj04yk", "type": "feedback"}, {"to": "in5aytjcakh3ax", "anon": "no", "when": "2016-04-18T05:50:33Z", "uid": "i0c90j8pjf56sn", "type": "followup"}, {"to": "in5aytjcakh3ax", "anon": "no", "when": "2016-04-18T06:15:01Z", "uid": "i2qc8h1kitx7dx", "type": "followup"}, {"to": "in5aytjcakh3ax", "anon": "no", "when": "2016-04-18T06:18:52Z", "uid": "i1ai2go9kl31o", "type": "feedback"}, {"to": "in5aytjcakh3ax", "anon": "no", "when": "2016-04-18T07:09:42Z", "uid": "i0cc5svdlda5i1", "type": "followup"}, {"to": "in5aytjcakh3ax", "anon": "no", "when": "2016-04-18T07:39:05Z", "uid": "ikvcvn2d1t77i8", "type": "followup"}, {"data": "in5psztnc8x71q", "anon": "no", "when": "2016-04-18T08:03:41Z", "uid": "i76z9sx78G8", "type": "update"}, {"data": "in5ptmdh5rg76k", "anon": "no", "when": "2016-04-18T08:04:10Z", "uid": "i76z9sx78G8", "type": "update"}, {"to": "in5aytjcakh3ax", "anon": "no", "when": "2016-04-18T08:04:42Z", "uid": "ikvcvq9428u7lc", "type": "followup"}, {"to": "in5aytjcakh3ax", "anon": "no", "when": "2016-04-18T08:38:57Z", "uid": "hzi9o0nrczmm5", "type": "followup"}, {"to": "in5aytjcakh3ax", "anon": "no", "when": "2016-04-18T08:54:27Z", "uid": "i6vkcot30qG", "type": "followup"}, {"to": "in5aytjcakh3ax", "anon": "no", "when": "2016-04-18T11:04:47Z", "uid": "ikw8wftavuy", "type": "followup"}, {"to": "in5aytjcakh3ax", "anon": "no", "when": "2016-04-18T11:06:43Z", "uid": "i2963rfujme1jy", "type": "followup"}, {"to": "in5aytjcakh3ax", "anon": "no", "when": "2016-04-18T11:41:42Z", "uid": "i107wegc5fe62e", "type": "followup"}, {"to": "in5aytjcakh3ax", "anon": "no", "when": "2016-04-18T11:55:23Z", "uid": "i0ciknt4jrm39r", "type": "followup"}, {"to": "in5aytjcakh3ax", "anon": "no", "when": "2016-04-18T11:56:41Z", "uid": "i6xklgt48XM", "type": "followup"}, {"to": "in5aytjcakh3ax", "anon": "no", "when": "2016-04-18T12:31:24Z", "uid": "i6wafl30cPn", "type": "followup"}, {"to": "in5aytjcakh3ax", "anon": "no", "when": "2016-04-18T13:00:28Z", "uid": "i0eqvqfbfgc1kf", "type": "followup"}, {"to": "in5aytjcakh3ax", "anon": "no", "when": "2016-04-18T13:14:22Z", "uid": "i17v31zfozkk7", "type": "followup"}, {"to": "in5aytjcakh3ax", "anon": "no", "when": "2016-04-18T14:18:06Z", "uid": "i0fzq77r8zy1yz", "type": "feedback"}, {"to": "in5aytjcakh3ax", "anon": "no", "when": "2016-04-18T14:21:22Z", "uid": "i18llvwgjbiq2", "type": "followup"}, {"to": "in5aytjcakh3ax", "anon": "no", "when": "2016-04-19T06:32:28Z", "uid": "i0nyfgp2bbqig", "type": "followup"}, {"to": "in5aytjcakh3ax", "anon": "no", "when": "2016-04-19T08:24:48Z", "uid": "hxfr6dv2fy44k8", "type": "followup"}, {"to": "in5aytjcakh3ax", "anon": "no", "when": "2016-04-19T08:57:20Z", "uid": "i0d74z7sxrr64l", "type": "followup"}, {"to": "in5aytjcakh3ax", "anon": "no", "when": "2016-04-19T09:39:17Z", "uid": "i13gciyp54r23v", "type": "followup"}, {"to": "in5aytjcakh3ax", "anon": "no", "when": "2016-04-19T09:59:05Z", "uid": "i0erwpmaxop73i", "type": "followup"}, {"to": "in5aytjcakh3ax", "anon": "no", "when": "2016-04-19T10:27:16Z", "uid": "i73gf9yzgUr", "type": "followup"}, {"to": "in5aytjcakh3ax", "anon": "no", "when": "2016-04-19T10:35:15Z", "uid": "i0gusoggvf72t6", "type": "followup"}, {"to": "in5aytjcakh3ax", "anon": "no", "when": "2016-04-19T10:55:56Z", "uid": "i0iaabhcht167g", "type": "followup"}, {"to": "in5aytjcakh3ax", "anon": "no", "when": "2016-04-19T11:06:36Z", "uid": "ilkj7zq365j7pd", "type": "followup"}, {"to": "in5aytjcakh3ax", "anon": "no", "when": "2016-04-19T11:19:31Z", "uid": "ikvcvp2hwon7k6", "type": "followup"}, {"to": "in5aytjcakh3ax", "anon": "no", "when": "2016-04-19T11:31:21Z", "uid": "i0cj8v3ojgo76l", "type": "followup"}, {"to": "in5aytjcakh3ax", "anon": "no", "when": "2016-04-19T11:39:13Z", "uid": "i0dvatlio3g3ju", "type": "followup"}, {"to": "in5aytjcakh3ax", "anon": "no", "when": "2016-04-19T11:45:29Z", "uid": "i6th9xfvp1kbv", "type": "feedback"}, {"to": "in5aytjcakh3ax", "anon": "no", "when": "2016-04-19T11:46:08Z", "uid": "i6th9xfvp1kbv", "type": "feedback"}, {"to": "in5aytjcakh3ax", "anon": "no", "when": "2016-04-19T11:59:44Z", "uid": "i6wafl30cPn", "type": "feedback"}, {"to": "in5aytjcakh3ax", "anon": "no", "when": "2016-04-19T12:45:50Z", "uid": "i6wafl30cPn", "type": "feedback"}, {"data": "in8hsggj7wj3r0", "anon": "no", "when": "2016-04-20T06:42:38Z", "uid": "i76z9sx78G8", "type": "update"}, {"data": "in8hur6p8xs3s4", "anon": "no", "when": "2016-04-20T06:44:25Z", "uid": "i76z9sx78G8", "type": "update"}, {"to": "in5aytjcakh3ax", "anon": "no", "when": "2016-04-21T06:55:00Z", "uid": "i17v31zfozkk7", "type": "feedback"}, {"data": "inaghsw884t2g8", "anon": "no", "when": "2016-04-21T15:41:53Z", "uid": "i76z9sx78G8", "type": "update"}, {"to": "in5aytjcakh3ax", "anon": "no", "when": "2016-04-30T11:13:46Z", "uid": "i14g50r7ui12pn", "type": "followup"}, {"to": "in5aytjcakh3ax", "anon": "no", "when": "2016-06-10T05:35:51Z", "uid": "i6uayp2ji1r", "type": "followup"}], "upvote_ids": [], "id": "in5aytjcakh3ax", "bookmarked": 57, "no_answer_followup": 2, "i_edits": [], "is_bookmarked": false, "children": [{"folders": [], "updated": "2016-04-18T01:24:42Z", "no_upvotes": 0, "uid": "i0b2fq3ezjw50r", "created": "2016-04-18T01:24:42Z", "type": "followup", "no_answer": 0, "id": "in5bjvyplim4en", "anon": "no", "bucket_name": "Week 4/17 - 4/23", "config": {}, "bucket_order": 12, "data": null, "children": [{"folders": [], "updated": "2016-04-18T06:18:52Z", "uid": "i1ai2go9kl31o", "created": "2016-04-18T06:18:52Z", "type": "feedback", "id": "in5m27gsxkr1fp", "anon": "no", "bucket_name": "Week 4/17 - 4/23", "config": {}, "bucket_order": 12, "data": null, "children": [], "subject": "<p></p>\n<p><a href=\"https://github.com/EudoraW/OS/blob/master/spoc/hw15/scheduler-homework.py\" target=\"_blank\">FIFO,SJF</a></p>"}], "subject": "<p>2013011391 张明瑞</p>\n<p>2013011392 吴之璟</p>\n<p></p>\n<p><a href=\"https://github.com/DrustZ/OS_SPOC_hw/blob/master/hw14/scheduler-homework.py\" target=\"_blank\">算法实现</a>&#xff08;目前&#xff09;:</p>\n<p>FIFO SJF RR</p>"}, {"folders": [], "updated": "2016-04-18T01:28:19Z", "no_upvotes": 0, "uid": "il7co2fpfTV", "created": "2016-04-18T01:28:19Z", "type": "followup", "no_answer": 0, "id": "in5bojttip96hi", "anon": "no", "bucket_name": "Week 4/17 - 4/23", "config": {}, "bucket_order": 12, "data": null, "children": [], "subject": "<p>2012010449 赵晟佳</p>\n<p>2012011393 高志锋</p>\n<p></p>\n<p><a href=\"https://github.com/ShengjiaZhao/ucore_lab/blob/master/related_info/schedule.py\" target=\"_blank\">stride算法实现</a></p>"}, {"folders": [], "updated": "2016-04-18T01:34:26Z", "no_upvotes": 0, "uid": "i0ckv5q1y0g3e3", "created": "2016-04-18T01:34:26Z", "type": "followup", "no_answer": 0, "id": "in5bwf7mmbl5cw", "anon": "no", "bucket_name": "Week 4/17 - 4/23", "config": {}, "bucket_order": 12, "data": null, "children": [], "subject": "<p>2013011338 王楠</p>\n<p>2013011342 徐炜杰</p>\n<p></p>\n<p><a target=\"_blank\" href=\"https://github.com/zliaky/POS2016/blob/master/SPOC/lec15/scheduler-homework.py\">算法实现</a></p>\n<p>目前实现&#xff1a;FIFO,SJF,RR,stride</p>"}, {"folders": [], "updated": "2016-04-18T01:37:18Z", "no_upvotes": 0, "uid": "i0cbq1nfv1m496", "created": "2016-04-18T01:37:18Z", "type": "followup", "no_answer": 0, "id": "in5c03ecf1h1as", "anon": "no", "bucket_name": "Week 4/17 - 4/23", "config": {}, "bucket_order": 12, "data": null, "children": [], "subject": "<p>马也 2013011365</p>\n<p>刘政宁 2013011362</p>\n<p><a href=\"https://github.com/lzhengning/OS2016/blob/master/SPOC/lect6-1/schedule-RR.py\" target=\"_blank\">RR算法</a></p>"}, {"folders": [], "updated": "2016-04-18T01:38:17Z", "no_upvotes": 0, "uid": "i0byevowhoc2ya", "created": "2016-04-18T01:38:17Z", "type": "followup", "no_answer": 0, "id": "in5c1cwz8cu2me", "anon": "no", "bucket_name": "Week 4/17 - 4/23", "config": {}, "bucket_order": 12, "data": null, "children": [], "subject": "<p><a href=\"https://d1b10bmlvqabco.cloudfront.net/attach/i5j09fnsl7k5x0/i0byevowhoc2ya/in5c0jawcli/schedulerhomework.py\" target=\"_blank\">schedulerhomework.py</a></p>\n<p>完成了123</p>\n<p>FIFO、SJF、RR</p>\n<p></p>\n<p>2013011393 冯栩</p>\n<p>2013011408 王梓仲</p>"}, {"folders": [], "updated": "2016-04-18T01:41:18Z", "no_upvotes": 0, "uid": "i0eqj2z1h2y55", "created": "2016-04-18T01:41:18Z", "type": "followup", "no_answer": 0, "id": "in5c593750g48f", "anon": "no", "bucket_name": "Week 4/17 - 4/23", "config": {}, "bucket_order": 12, "data": null, "children": [], "subject": "<p>黄世宇 2013011304</p>\n<p>李成江 2013011305</p>\n<p><a href=\"https://github.com/HSYLCJ/OS_ExerciseAnwer/blob/master/06-1-spoc-discussion-Answer/scheduler-homework.py\" target=\"_blank\">CODE</a></p>\n<p>目前已完成算法</p>\n<p>(1)FIFO, (2)SJF</p>\n<p></p>"}, {"folders": [], "updated": "2016-04-18T01:46:43Z", "no_upvotes": 0, "uid": "i0f3rp5o38h4mk", "created": "2016-04-18T01:46:43Z", "type": "followup", "no_answer": 0, "id": "in5cc7vel0fnr", "anon": "no", "bucket_name": "Week 4/17 - 4/23", "config": {}, "bucket_order": 12, "data": null, "children": [{"folders": [], "updated": "2016-04-18T02:18:47Z", "uid": "i0b0ihyxqrc2ej", "created": "2016-04-18T02:18:47Z", "type": "feedback", "id": "in5dhg1uakz66z", "anon": "no", "bucket_name": "Week 4/17 - 4/23", "config": {}, "bucket_order": 12, "data": null, "children": [], "subject": "<p><a href=\"https://github.com/thudzj/Operating-System-Course-2016-Spring/blob/4db2a1c3a1a6d326baeb455fb7bd52187d6d1c19/week9/schedule-revert.py\" target=\"_blank\">优先级反置</a></p>\n<p>使用&#xff1a;python scheduler-homework.py -p RE</p>"}], "subject": "<p>邓志杰 2013011359</p>\n<p>杨志灿 2013011377</p>\n<p><a href=\"https://github.com/coolyangzc/Operating-System-Course-2016-Spring/blob/master/week9/scheduler-homework.py\" target=\"_blank\">FIFO/SJF/RR</a></p>"}, {"folders": [], "updated": "2016-04-18T01:55:46Z", "no_upvotes": 0, "uid": "ikwla6afpqb", "created": "2016-04-18T01:55:46Z", "type": "followup", "no_answer": 0, "id": "in5cnugzeel6xr", "anon": "no", "bucket_name": "Week 4/17 - 4/23", "config": {}, "bucket_order": 12, "data": null, "children": [{"folders": [], "updated": "2016-04-18T02:24:44Z", "uid": "ikvcvmupe4x7i1", "created": "2016-04-18T02:24:44Z", "type": "feedback", "id": "in5dp3gictq6z1", "anon": "no", "bucket_name": "Week 4/17 - 4/23", "config": {}, "bucket_order": 12, "data": null, "children": [], "subject": "<p><a href=\"https://github.com/hhLeo/OS2016/blob/master/os_course_spoc_exercises/06-1-spoc-discussion/scheduler-RR.py\" target=\"_blank\">RR</a></p>"}], "subject": "<p>2013011331黄欢</p>\n<p>2013011425蔡文静</p>\n<p><a href=\"https://github.com/hhLeo/OS2016/blob/master/os_course_spoc_exercises/06-1-spoc-discussion/scheduler-SJF.py\" target=\"_blank\">scheduler - FIFO &amp; SJF</a></p>"}, {"folders": [], "updated": "2016-04-18T02:01:08Z", "no_upvotes": 0, "uid": "i0f97hpgaug3eu", "created": "2016-04-18T02:01:08Z", "type": "followup", "no_answer": 0, "id": "in5curahga930o", "anon": "no", "bucket_name": "Week 4/17 - 4/23", "config": {}, "bucket_order": 12, "data": null, "children": [], "subject": "<p>徐磊 2013011344</p>\n<p>韩旭 2013011343</p>\n<p></p>\n<p><a href=\"https://github.com/THUCSTHanxu13/OS2016/tree/master/09-1-spoc\" target=\"_blank\">[GitHub]</a> 实现了SJF&#xff0c;考虑了job的arrive time。</p>"}, {"folders": [], "updated": "2016-04-18T02:02:26Z", "no_upvotes": 0, "uid": "i0d7xnweuzw2k2", "created": "2016-04-18T02:02:26Z", "type": "followup", "no_answer": 0, "id": "in5cwey39bv4nx", "anon": "no", "bucket_name": "Week 4/17 - 4/23", "config": {}, "bucket_order": 12, "data": null, "children": [], "subject": "<p>马志远 2013011357</p>\n<p>施韶韵 2013011358</p>\n<p></p>\n<p>FIFO, SJF, RR (目前)</p>\n<p><a href=\"https://github.com/Shuriken13/spoc_exercises/blob/master/20160418/scheduler-homework.py\">https://github.com/Shuriken13/spoc_exercises/blob/master/20160418/scheduler-homework.py</a></p>\n<p></p>"}, {"folders": [], "updated": "2016-04-18T02:02:44Z", "no_upvotes": 0, "uid": "i6swz3atggR", "created": "2016-04-18T02:02:44Z", "type": "followup", "no_answer": 0, "id": "in5cwt67jww3md", "anon": "no", "bucket_name": "Week 4/17 - 4/23", "config": {}, "bucket_order": 12, "data": null, "children": [], "subject": "<p>柯均洁 2012011335</p>\n<p>赵诚辉 2012011384</p>\n<p></p>\n<p><a href=\"https://github.com/junjiek/ucore_os_lab/blob/master/related_info/lab6/scheduler-homework.py\" target=\"_blank\">FIFO/SJF/RR</a></p>"}, {"folders": [], "updated": "2016-04-18T02:21:29Z", "no_upvotes": 0, "uid": "i0er21z2bhp4dk", "created": "2016-04-18T02:21:29Z", "type": "followup", "no_answer": 0, "id": "in5dkxekpfr1f6", "anon": "no", "bucket_name": "Week 4/17 - 4/23", "config": {}, "bucket_order": 12, "data": null, "children": [{"folders": [], "updated": "2016-04-18T04:01:23Z", "uid": "i0f453lqmj04yk", "created": "2016-04-18T04:01:23Z", "type": "feedback", "id": "in5h5dym6u44ky", "anon": "no", "bucket_name": "Week 4/17 - 4/23", "config": {}, "bucket_order": 12, "data": null, "children": [], "subject": "<p>更新&#xff1a;增加了<a href=\"https://github.com/liufeng13/os_course_spoc_exercises/blob/master/all/6-2spoc_FIFO_SJF_RR_STRIDE_MLFQ.py\" target=\"_blank\">MLFQ和STRIDE</a></p>"}], "subject": "<p>2013011427 刘智峰</p>\n<p>2013011420 刘峰</p>\n<p></p>\n<p><a target=\"_blank\" href=\"https://github.com/liuzf13/os_course_spoc_exercises/blob/master/all/schedule.py\">FIFO/SJF/RR</a></p>"}, {"folders": [], "updated": "2016-04-18T02:32:00Z", "no_upvotes": 0, "uid": "i0et95bli7r7ky", "created": "2016-04-18T02:32:00Z", "type": "followup", "no_answer": 0, "id": "in5dyfvycwh5yg", "anon": "no", "bucket_name": "Week 4/17 - 4/23", "config": {}, "bucket_order": 12, "data": null, "children": [{"folders": [], "updated": "2016-04-18T02:32:30Z", "uid": "i0et95bli7r7ky", "created": "2016-04-18T02:32:30Z", "type": "feedback", "id": "in5dz2vh2m56qx", "anon": "no", "bucket_name": "Week 4/17 - 4/23", "config": {}, "bucket_order": 12, "data": null, "children": [], "subject": "<p><a href=\"https://github.com/JudyYe/os_homework/tree/master/9-1\" target=\"_blank\">FIFO/RR</a></p>"}, {"folders": [], "updated": "2016-04-18T03:32:37Z", "uid": "ikvcvnm9rrk7is", "created": "2016-04-18T03:32:37Z", "type": "feedback", "id": "in5g4eepiov6oe", "anon": "no", "bucket_name": "Week 4/17 - 4/23", "config": {}, "bucket_order": 12, "data": null, "children": [], "subject": "<p><a href=\"https://github.com/yu-huang13/OS_HY/tree/master/06-1-spoc\" target=\"_blank\">FIFO/SJF/RR/MLFQ</a></p>"}], "subject": "<p>黄予 2013011363</p>\n<p>叶雨菲 2013011325</p>"}, {"folders": [], "updated": "2016-04-18T02:36:04Z", "no_upvotes": 0, "uid": "ie7xy6atuuc1re", "created": "2016-04-18T02:36:04Z", "type": "followup", "no_answer": 0, "id": "in5e3oq1smc3gn", "anon": "no", "bucket_name": "Week 4/17 - 4/23", "config": {}, "bucket_order": 12, "data": null, "children": [], "subject": "<p>第二组</p>\n<p>2011011384 郑玉昆</p>\n<p>2013011375 茹逸中</p>\n<p></p>\n<p>RR算法&#xff1a;<a href=\"https://github.com/zhengyk11/ucore_lab_docs/tree/master/06-1-spoc-discussion\" target=\"_blank\">https://github.com/zhengyk11/ucore_lab_docs/tree/master/06-1-spoc-discussion</a></p>"}, {"folders": [], "updated": "2016-04-18T02:38:48Z", "no_upvotes": 0, "uid": "i81jxkfelf72a9", "created": "2016-04-18T02:38:48Z", "type": "followup", "no_answer": 0, "id": "in5e76ku2a23hd", "anon": "no", "bucket_name": "Week 4/17 - 4/23", "config": {}, "bucket_order": 12, "data": null, "children": [], "subject": "<p>2012011380 张敬卿</p>\n<p>2012011297 李雪</p>\n<p></p>\n<p><a href=\"https://github.com/lixue12/os_course_spoc_exercises/blob/master/schedular.py\" target=\"_blank\">FIFO/SJF/RR</a></p>"}, {"folders": [], "updated": "2016-04-18T03:02:02Z", "no_upvotes": 0, "uid": "i0anp25rzjk2wt", "created": "2016-04-18T03:02:02Z", "type": "followup", "no_answer": 0, "id": "in5f125w1ms4pu", "anon": "no", "bucket_name": "Week 4/17 - 4/23", "config": {}, "bucket_order": 12, "data": null, "children": [], "subject": "<p>2013011380 陈昺弘</p>\n<p>2013011384 马坚鑫</p>\n<p></p>\n<p><a href=\"https://github.com/JianxinMa/os-spoc/blob/master/spoc-17.md\" target=\"_blank\">https://github.com/JianxinMa/os-spoc/blob/master/spoc-17.md</a></p>"}, {"folders": [], "updated": "2016-04-18T05:50:33Z", "no_upvotes": 0, "uid": "i0c90j8pjf56sn", "created": "2016-04-18T05:50:33Z", "type": "followup", "no_answer": 0, "id": "in5l1s00spe21t", "anon": "no", "bucket_name": "Week 4/17 - 4/23", "config": {}, "bucket_order": 12, "data": null, "children": [], "subject": "<p>姜天健 2013011360</p>\n<p>桥本优 2013011370</p>\n<p></p>\n<p><a href=\"https://github.com/Response777/OS2016/blob/master/spoc15/report.md\" target=\"_blank\">https://github.com/Response777/OS2016/blob/master/spoc15/report.md</a></p>\n<p></p>\n<p>使用优先级继承解决优先级反置</p>"}, {"folders": [], "updated": "2016-04-18T06:15:01Z", "no_upvotes": 0, "uid": "i2qc8h1kitx7dx", "created": "2016-04-18T06:15:01Z", "type": "followup", "no_answer": 0, "id": "in5lx8z31mcwn", "anon": "no", "bucket_name": "Week 4/17 - 4/23", "config": {}, "bucket_order": 12, "data": null, "children": [], "subject": "<p>陈文潇 2013011317</p>\n<p>https://github.com/chenwenxiao/OS/tree/master/hw13</p>"}, {"folders": [], "updated": "2016-04-18T07:09:42Z", "no_upvotes": 0, "uid": "i0cc5svdlda5i1", "created": "2016-04-18T07:09:42Z", "type": "followup", "no_answer": 0, "id": "in5nvkv2h855hh", "anon": "no", "bucket_name": "Week 4/17 - 4/23", "config": {}, "bucket_order": 12, "data": null, "children": [], "subject": "<p>钱雨杰 2013011372</p>\n<p>董胤蓬 2013011367</p>\n<p></p>\n<p><a href=\"https://github.com/thomas0809/os/blob/master/lec15/scheduler-homework.py\">https://github.com/thomas0809/os/blob/master/lec15/scheduler-homework.py</a></p>\n<p>实现了FIFO/SJF/RR/MLFQ</p>\n<p>示例使用方式&#xff1a;python scheduler-homework.py -p MLFQ</p>"}, {"folders": [], "updated": "2016-04-18T07:39:05Z", "no_upvotes": 0, "uid": "ikvcvn2d1t77i8", "created": "2016-04-18T07:39:05Z", "type": "followup", "no_answer": 0, "id": "in5oxd44dwm3ya", "anon": "no", "bucket_name": "Week 4/17 - 4/23", "config": {}, "bucket_order": 12, "data": null, "children": [], "subject": "<p>2013011332 卢枫</p>\n<p>2013011350 古裔正</p>\n<p></p>\n<p><a href=\"https://github.com/lufeng13/os_spoc_discussion/blob/master/scheduler-homework.py\" target=\"_blank\">FIFO/RR/stride</a></p>"}, {"folders": [], "updated": "2016-04-18T08:04:42Z", "no_upvotes": 0, "uid": "ikvcvq9428u7lc", "created": "2016-04-18T08:04:42Z", "type": "followup", "no_answer": 0, "id": "in5puavdxoc1wl", "anon": "no", "bucket_name": "Week 4/17 - 4/23", "config": {}, "bucket_order": 12, "data": null, "children": [], "subject": "<p><a href=\"https://github.com/2012011391/os_course_spoc_exercises/blob/master/spoc15-scheduler-homework.py\" target=\"_blank\">https://github.com/2012011391/os_course_spoc_exercises/blob/master/spoc15-scheduler-homework.py</a></p>\n<p>孙兴法2012011391</p>\n<p>石道明2012011387</p>\n<p>实现&#xff1a;FIFO(自带)/SJF</p>"}, {"folders": [], "updated": "2016-04-18T08:38:57Z", "no_upvotes": 0, "uid": "hzi9o0nrczmm5", "created": "2016-04-18T08:38:57Z", "type": "followup", "no_answer": 0, "id": "in5r2c7w3f543u", "anon": "no", "bucket_name": "Week 4/17 - 4/23", "config": {}, "bucket_order": 12, "data": null, "children": [], "subject": "<p>谢云飞  2013011428</p>\n<p>刘春建  2013011417</p>\n<p><a href=\"https://github.com/xieyf13/OS_SPOC_KEY/blob/master/06-1-2.py\" target=\"_blank\">FIFO/SJF</a></p>"}, {"folders": [], "updated": "2016-04-18T08:54:27Z", "no_upvotes": 0, "uid": "i6vkcot30qG", "created": "2016-04-18T08:54:27Z", "type": "followup", "no_answer": 0, "id": "in5rm9vxcmj53b", "anon": "no", "bucket_name": "Week 4/17 - 4/23", "config": {}, "bucket_order": 12, "data": null, "children": [{"folders": [], "updated": "2016-04-19T11:45:29Z", "uid": "i6th9xfvp1kbv", "created": "2016-04-19T11:45:29Z", "type": "feedback", "id": "in7d63azabm6ja", "anon": "no", "bucket_name": "Week 4/17 - 4/23", "config": {}, "bucket_order": 12, "data": null, "children": [], "subject": "<p><a href=\"https://github.com/wonda/os_exercises/blob/master/all/scheduler-homework.py\" target=\"_blank\">优先级反置</a></p>"}, {"folders": [], "updated": "2016-04-19T11:46:08Z", "uid": "i6th9xfvp1kbv", "created": "2016-04-19T11:46:08Z", "type": "feedback", "id": "in7d6x5asf83ux", "anon": "no", "bucket_name": "Week 4/17 - 4/23", "config": {}, "bucket_order": 12, "data": null, "children": [], "subject": "<p>测试&#xff1a;python scheduler-homework.py -p PI</p>"}], "subject": "<p>2012011370 魏洪浩<br />2012011279 李德旺</p>"}, {"folders": [], "updated": "2016-04-18T11:04:47Z", "no_upvotes": 0, "uid": "ikw8wftavuy", "created": "2016-04-18T11:04:47Z", "type": "followup", "no_answer": 0, "id": "in5w9vs7r3y64l", "anon": "no", "bucket_name": "Week 4/17 - 4/23", "config": {}, "bucket_order": 12, "data": null, "children": [], "subject": "<p>2013012444 易坤</p>\n<p>2013011341 吴铮</p>\n<p><a href=\"https://github.com/jamesthu/exercise/blob/master/17.py\" target=\"_blank\">FIFO/SJF/RR/stride</a></p>"}, {"folders": [], "updated": "2016-04-18T11:06:43Z", "no_upvotes": 0, "uid": "i2963rfujme1jy", "created": "2016-04-18T11:06:43Z", "type": "followup", "no_answer": 0, "id": "in5wcd6ytne4ce", "anon": "no", "bucket_name": "Week 4/17 - 4/23", "config": {}, "bucket_order": 12, "data": null, "children": [{"folders": [], "updated": "2016-04-18T14:18:06Z", "uid": "i0fzq77r8zy1yz", "created": "2016-04-18T14:18:06Z", "type": "feedback", "id": "in636i3bekh1cu", "anon": "no", "bucket_name": "Week 4/17 - 4/23", "config": {}, "bucket_order": 12, "data": null, "children": [], "subject": "<p><a href=\"https://github.com/nanancy/OS2016/blob/master/lec15/MLFQ.cpp\" target=\"_blank\">新增加含IO机制的MFSQ</a></p>"}], "subject": "<p>游宇铭  2013011386</p>\n<p>何晓楠  2013011361</p>\n<p><a href=\"https://github.com/nanancy/OS2016/tree/master/lec15\" target=\"_blank\">SJF</a></p>"}, {"folders": [], "updated": "2016-04-18T11:41:42Z", "no_upvotes": 0, "uid": "i107wegc5fe62e", "created": "2016-04-18T11:41:42Z", "type": "followup", "no_answer": 0, "id": "in5xlczgagvc4", "anon": "no", "bucket_name": "Week 4/17 - 4/23", "config": {}, "bucket_order": 12, "data": null, "children": [], "subject": "<p>2013012109  张哲宇</p>\n<p>EDF: <a href=\"https://d1b10bmlvqabco.cloudfront.net/attach/i5j09fnsl7k5x0/i107wegc5fe62e/in5xl36fxqlu/edf.cpp\" target=\"_blank\">edf.cpp</a></p>"}, {"folders": [], "updated": "2016-04-18T11:55:23Z", "no_upvotes": 0, "uid": "i0ciknt4jrm39r", "created": "2016-04-18T11:55:23Z", "type": "followup", "no_answer": 0, "id": "in5y2yz7iup6zp", "anon": "no", "bucket_name": "Week 4/17 - 4/23", "config": {}, "bucket_order": 12, "data": null, "children": [], "subject": "<p>吴永宇 2013011424</p>\n<p></p>\n<p>吴孟轩 213011421</p>\n<p></p>\n<p><a href=\"https://github.com/wu-yy/SPOC15/blob/master/answer.py\" target=\"_blank\">答案</a></p>"}, {"folders": [], "updated": "2016-04-18T11:56:41Z", "no_upvotes": 0, "uid": "i6xklgt48XM", "created": "2016-04-18T11:56:41Z", "type": "followup", "no_answer": 0, "id": "in5y4mm34oe2dx", "anon": "no", "bucket_name": "Week 4/17 - 4/23", "config": {}, "bucket_order": 12, "data": null, "children": [], "subject": "<p><a href=\"https://github.com/knightsing/os_exercises/blob/master/8-1/lecture9-1.py\" target=\"_blank\">answer</a></p>\n<p>2012011396谢雷振</p>\n<p>2012011386张景哲</p>"}, {"folders": [], "updated": "2016-04-18T12:31:24Z", "no_upvotes": 0, "uid": "i6wafl30cPn", "created": "2016-04-18T12:31:24Z", "type": "followup", "no_answer": 0, "id": "in5zd9s2oo75o", "anon": "no", "bucket_name": "Week 4/17 - 4/23", "config": {}, "bucket_order": 12, "data": null, "children": [{"folders": [], "updated": "2016-04-19T11:59:44Z", "uid": "i6wafl30cPn", "created": "2016-04-19T11:59:44Z", "type": "feedback", "id": "in7doelure731y", "anon": "no", "bucket_name": "Week 4/17 - 4/23", "config": {}, "bucket_order": 12, "data": null, "children": [], "subject": "<p><a href=\"https://github.com/hanshan3290/OS_HW/blob/master/scheduler-homework.py\" target=\"_blank\">https://github.com/hanshan3290/OS_HW/blob/master/scheduler-homework.py</a></p>"}, {"folders": [], "updated": "2016-04-19T12:45:50Z", "uid": "i6wafl30cPn", "created": "2016-04-19T12:45:50Z", "type": "feedback", "id": "in7fbon5xva3p0", "anon": "no", "bucket_name": "Week 4/17 - 4/23", "config": {}, "bucket_order": 12, "data": null, "children": [], "subject": "<p>7. RM</p>"}], "subject": "<p>2012011486 张洵恺</p>\n<p>2012013290 韩珊</p>"}, {"folders": [], "updated": "2016-04-18T13:00:28Z", "no_upvotes": 0, "uid": "i0eqvqfbfgc1kf", "created": "2016-04-18T13:00:28Z", "type": "followup", "no_answer": 0, "id": "in60enpj3js5fc", "anon": "no", "bucket_name": "Week 4/17 - 4/23", "config": {}, "bucket_order": 12, "data": null, "children": [], "subject": "<p>2013011430 陈冲</p>\n<p>2013011426 赖涵光</p>\n<p><a href=\"https://github.com/cstchenc/Spoc15/blob/master/anwser.py\" target=\"_blank\">FIFO_SJF_RR_STRIDE_MLFQ</a></p>"}, {"folders": [], "updated": "2016-04-18T13:14:22Z", "no_upvotes": 0, "uid": "i17v31zfozkk7", "created": "2016-04-18T13:14:22Z", "type": "followup", "no_answer": 0, "id": "in60wjky1s82sw", "anon": "no", "bucket_name": "Week 4/17 - 4/23", "config": {}, "bucket_order": 12, "data": null, "children": [{"folders": [], "updated": "2016-04-21T06:55:00Z", "uid": "i17v31zfozkk7", "created": "2016-04-21T06:55:00Z", "type": "feedback", "id": "in9xo810dr12vm", "anon": "no", "bucket_name": "Week 4/17 - 4/23", "config": {}, "bucket_order": 12, "data": null, "children": [], "subject": "<p>非常抱歉&#xff0c;把何小豪的学号打错 应该是 2013011335</p>"}], "subject": "<p>郭志芃 2013011348</p>\n<p>何小豪 2013011355</p>\n<p></p>\n<p>理解并实现优先级反置方法&#xff1a;</p>\n<p><a href=\"https://github.com/gzp9595/OS2016spring/blob/master/lec15/scheduler-homework.py\">https://github.com/gzp9595/OS2016spring/blob/master/lec15/scheduler-homework.py</a></p>\n<p></p>"}, {"folders": [], "updated": "2016-04-18T14:21:22Z", "no_upvotes": 0, "uid": "i18llvwgjbiq2", "created": "2016-04-18T14:21:22Z", "type": "followup", "no_answer": 0, "id": "in63ap2go3a4ld", "anon": "no", "bucket_name": "Week 4/17 - 4/23", "config": {}, "bucket_order": 12, "data": null, "children": [], "subject": "<p>陈志鹏 2013011330</p>\n<p><a href=\"https://github.com/LMCW/OS2016/blob/master/scheduler-homework.py\">https://github.com/LMCW/OS2016/blob/master/scheduler-homework.py</a></p>\n<p>RR算法</p>"}, {"folders": [], "updated": "2016-04-19T06:32:28Z", "no_upvotes": 0, "uid": "i0nyfgp2bbqig", "created": "2016-04-19T06:32:28Z", "type": "followup", "no_answer": 0, "id": "in71zjc852k5wn", "anon": "no", "bucket_name": "Week 4/17 - 4/23", "config": {}, "bucket_order": 12, "data": null, "children": [], "subject": "<p>许孝先 2013011423  张建业 2013011419</p>\n<p>https://github.com/xuxx13/XUXX/blob/master/mlfq.py</p>"}, {"folders": [], "updated": "2016-04-19T08:24:48Z", "no_upvotes": 0, "uid": "hxfr6dv2fy44k8", "created": "2016-04-19T08:24:48Z", "type": "followup", "no_answer": 0, "id": "in75zztgtdj3rr", "anon": "no", "bucket_name": "Week 4/17 - 4/23", "config": {}, "bucket_order": 12, "data": null, "children": [], "subject": "<p>2011010870 杨凯峪 </p>\n<p>2012011487  徐梓哲</p>\n<p><a target=\"_blank\">https://github.com/yangky11/os_course_spoc_exercises/blob/master/lec15.py</a></p>\n<p></p>\n<p></p>"}, {"folders": [], "updated": "2016-04-19T08:57:20Z", "no_upvotes": 0, "uid": "i0d74z7sxrr64l", "created": "2016-04-19T08:57:20Z", "type": "followup", "no_answer": 0, "id": "in775uhbtmgeq", "anon": "no", "bucket_name": "Week 4/17 - 4/23", "config": {}, "bucket_order": 12, "data": null, "children": [], "subject": "<p>张俊祺   2013011436</p>\n<p>刘元凯   2013011431</p>\n<p><a href=\"https://github.com/zhangjunqi13/lec15/blob/master/answer\" target=\"_blank\">优先级反置方法</a></p>"}, {"folders": [], "updated": "2016-04-19T09:39:17Z", "no_upvotes": 0, "uid": "i13gciyp54r23v", "created": "2016-04-19T09:39:17Z", "type": "followup", "no_answer": 0, "id": "in78nsmo69a2dv", "anon": "no", "bucket_name": "Week 4/17 - 4/23", "config": {}, "bucket_order": 12, "data": null, "children": [], "subject": "<p>张正 2013011418</p>\n<p><a href=\"https://github.com/zhangzheng-thu/os_course_spoc_exercises-1/blob/master/all/SJF.py\" target=\"_blank\">SJF</a></p>"}, {"folders": [], "updated": "2016-04-19T09:59:05Z", "no_upvotes": 0, "uid": "i0erwpmaxop73i", "created": "2016-04-19T09:59:05Z", "type": "followup", "no_answer": 0, "id": "in79d98ve7g1kn", "anon": "no", "bucket_name": "Week 4/17 - 4/23", "config": {}, "bucket_order": 12, "data": null, "children": [], "subject": "<p>2013011352  张宇翔</p>\n<p>2013011326  周建宇</p>\n<p>FIFO/SJF/RR&#xff1a;<a href=\"https://github.com/ZhouDavid/os-spoc/blob/master/lec13/scheduler.py\" target=\"_blank\">https://github.com/ZhouDavid/os-spoc/blob/master/lec13/scheduler.py</a></p>\n<p>EDF: <a href=\"https://github.com/ZhouDavid/os-spoc/blob/master/lec13/spoc11-EDF.cpp\" target=\"_blank\">https://github.com/ZhouDavid/os-spoc/blob/master/lec13/spoc11-EDF.cpp</a></p>"}, {"folders": [], "updated": "2016-04-19T10:27:16Z", "no_upvotes": 0, "uid": "i73gf9yzgUr", "created": "2016-04-19T10:27:16Z", "type": "followup", "no_answer": 0, "id": "in7adhk52kb70", "anon": "no", "bucket_name": "Week 4/17 - 4/23", "config": {}, "bucket_order": 12, "data": null, "children": [], "subject": "<p>2012011377  武桐</p>\n<p>2012011381  丁弼原</p>\n<p><a href=\"https://github.com/wt9431/os_course_spoc_exercises/blob/master/answers/scheduler-homework.py\">https://github.com/wt9431/os_course_spoc_exercises/blob/master/answers/scheduler-homework.py</a></p>\n<p></p>"}, {"folders": [], "updated": "2016-04-19T10:35:15Z", "no_upvotes": 0, "uid": "i0gusoggvf72t6", "created": "2016-04-19T10:35:15Z", "type": "followup", "no_answer": 0, "id": "in7anrks7vh3i9", "anon": "no", "bucket_name": "Week 4/17 - 4/23", "config": {}, "bucket_order": 12, "data": null, "children": [], "subject": "<p>吕国南 2013011337</p>\n<p><a href=\"https://github.com/yuejinzhao/os_SPOC/blob/master/09-1-spoc/scheduler-homework.py\" target=\"_blank\">SJF</a></p>"}, {"folders": [], "updated": "2016-04-19T10:55:56Z", "no_upvotes": 0, "uid": "i0iaabhcht167g", "created": "2016-04-19T10:55:56Z", "type": "followup", "no_answer": 0, "id": "in7becu13jw1fz", "anon": "no", "bucket_name": "Week 4/17 - 4/23", "config": {}, "bucket_order": 12, "data": null, "children": [], "subject": "<p>高胜寒 2013011400</p>\n<p>蒋文明 2013011388</p>\n<p>RR算法</p>\n<p><a href=\"https://github.com/gaosh13/ucore_os_lab/blob/master/related_info/lab6/scheduler-homework.py\">https://github.com/gaosh13/ucore_os_lab/blob/master/related_info/lab6/scheduler-homework.py</a></p>\n<p></p>"}, {"folders": [], "updated": "2016-04-19T11:06:36Z", "no_upvotes": 0, "uid": "ilkj7zq365j7pd", "created": "2016-04-19T11:06:36Z", "type": "followup", "no_answer": 0, "id": "in7bs2zgbq23jp", "anon": "no", "bucket_name": "Week 4/17 - 4/23", "config": {}, "bucket_order": 12, "data": null, "children": [], "subject": "<p>杨煜 2011010312</p>\n<p>卓有为 2012011329</p>\n<p><a href=\"https://github.com/thuyangyu/os_exercises/blob/master/9-1/scheduler-homework.py\" target=\"_blank\">FIFO</a></p>"}, {"folders": [], "updated": "2016-04-19T11:19:31Z", "no_upvotes": 0, "uid": "ikvcvp2hwon7k6", "created": "2016-04-19T11:19:31Z", "type": "followup", "no_answer": 0, "id": "in7c8p1prl3ai", "anon": "no", "bucket_name": "Week 4/17 - 4/23", "config": {}, "bucket_order": 12, "data": null, "children": [], "subject": "<p>王子愉2013011300</p>\n<p>FIFO/ SJF/RR/stride</p>\n<p><a href=\"https://d1b10bmlvqabco.cloudfront.net/attach/i5j09fnsl7k5x0/ikvcvp2hwon7k6/in7c5nwauvbb/code.py\" target=\"_blank\">code.py</a></p>"}, {"folders": [], "updated": "2016-04-19T11:31:21Z", "no_upvotes": 0, "uid": "i0cj8v3ojgo76l", "created": "2016-04-19T11:31:21Z", "type": "followup", "no_answer": 0, "id": "in7cnwv8sqf2h9", "anon": "no", "bucket_name": "Week 4/17 - 4/23", "config": {}, "bucket_order": 12, "data": null, "children": [], "subject": "<p>王聪 2013011429</p>\n<p>雷鑫 2013011437</p>\n<p><a href=\"https://github.com/congwang13/solution1/blob/master/edf.cpp\" target=\"_blank\">EDF</a></p>"}, {"folders": [], "updated": "2016-04-19T11:39:13Z", "no_upvotes": 0, "uid": "i0dvatlio3g3ju", "created": "2016-04-19T11:39:13Z", "type": "followup", "no_answer": 0, "id": "in7cy180x3a4vu", "anon": "no", "bucket_name": "Week 4/17 - 4/23", "config": {}, "bucket_order": 12, "data": null, "children": [], "subject": "<p>郭晓阳(2013011554)<br />陈雨兰(2013011415)</p>\n<p>&#39;FIFO&#39; &#39;SJF&#39; &#39;RR&#39;</p>\n<p><a href=\"https://github.com/guoxy95/OS_quiz/blob/master/scheduler-homework.py\" target=\"_blank\">https://github.com/guoxy95/OS_quiz/blob/master/scheduler-homework.py</a></p>"}, {"folders": [], "updated": "2016-04-30T11:13:46Z", "no_upvotes": 0, "uid": "i14g50r7ui12pn", "created": "2016-04-30T11:13:46Z", "type": "followup", "no_answer": 1, "id": "inn1vo6djgb49o", "anon": "no", "bucket_name": "Week 4/24 - 4/30", "config": {}, "bucket_order": 11, "data": null, "children": [], "subject": "<p>2013011319 龙浩民</p>\n<p> </p>\n<p><a href=\"https://github.com/cherudim9/SPOC/blob/master/SPOC15.py\" target=\"_blank\">python代码实现的优先级置换算法</a></p>\n<p>&#xff08;我删去了优先级置换算法不需要的部分源代码&#xff09;</p>\n<p> </p>\n<p><strong>注&#xff1a;助教老师您好&#xff0c;由于上周&#xff08;2016/04/17~2016/04/24&#xff09;我前往武汉参加比赛&#xff0c;所以本次SPOC没有按时完成&#xff0c;非常抱歉&#xff01;现已补做。</strong></p>"}, {"folders": [], "updated": "2016-06-10T05:35:51Z", "no_upvotes": 0, "uid": "i6uayp2ji1r", "created": "2016-06-10T05:35:51Z", "type": "followup", "no_answer": 1, "id": "ip9av0te57e44t", "anon": "no", "bucket_name": "Today", "config": {}, "bucket_order": 2, "data": null, "children": [], "subject": "<p>2012011289 姚宇轩 spoc15&#xff1a;https://github.com/yyxstorm/os_course_spoc_exercises/blob/master/all/06-1-spoc-discussion.md</p>"}], "nr": 806, "bucket_order": 2, "config": {}, "status": "active", "tags": ["instructor-note", "课堂问答"], "num_favorites": 1, "bucket_name": "Today", "q_edits": [], "data": {"embed_links": []}, "request_instructor": 0, "created": "2016-04-18T01:08:19Z", "is_tag_good": false, "type": "note", "s_edits": [], "my_favorite": false, "default_anonymity": "no", "t": 1465572618117, "tag_good": [], "tag_good_arr": [], "history": [{"content": "<p></p>\n<h1>2016春季-第15讲 课堂思考题回答-陈渝班</h1>\n<div>\n<p>请陈渝班的同学把“第十五讲 处理机调度”中指定小题的回答结果写在此贴中对应题目后面。</p>\n<p> </p>\n<p><a href=\"https://github.com/chyyuu/os_course_spoc_exercises/blob/master/all/06-1-spoc-discussion.md#小组练习与思考题\" target=\"_blank\">https://github.com/chyyuu/os_course_spoc_exercises/blob/master/all/06-1-spoc-discussion.md#小组练习与思考题</a></p>\n<p> </p>\n<p>第15讲的回答的截止时间是明天&#xff08;20160419&#xff09;晚20点前。<br /><br />要求&#xff1a;</p>\n<p>有8个“小组练习与思考题”&#xff0c;最多二个人一组&#xff0c;也可以独立回答。依据小组成员学号中最小学号除8后的余数&#xff0c;完成与余数&#43;1相同的题目。</p>\n<p> </p>\n<p><a href=\"https://github.com/chyyuu/os_course_spoc_exercises/blob/master/all/06-1-spoc-discussion.md#小组练习与思考题\" target=\"_blank\">https://github.com/chyyuu/os_course_spoc_exercises/blob/master/all/06-1-spoc-discussion.md#小组练习与思考题</a></p>\n<p> </p>\n<p>(1)理解并实现FIFO调度算法<br />(2)理解并实现SJF调度算法<br />(3)理解并实现RR调度算法<br />(4)理解并实现MLFQ调度算法<br />(5)理解并实现stride调度算法<br />(6)理解并实现EDF实时调度算法<br />(7)理解并实现RM实时调度算法<br />(8)理解并实现优先级反置方法</p>\n<p> </p>\n<p>注意&#xff0c;会检查完成情况&#xff0c;没有正确完成的同学算没有提交&#xff0c;尽量都放在github上&#xff0c;不要用网盘上传&#xff0c;有时候打不开。</p>\n<p>优胜者&#xff1a;</p>\n<p>杨志灿 2013011377 <br />邓志杰 2013011359<br />郑玉昆 2011011384<br />茹逸中 2013011375</p>\n<p>何晓楠 2013011361<br />游宇铭 2013011386</p>\n<p>陈昺弘 2013011380 </p>\n<p>马坚鑫 2013011384 </p>\n<p>未完成的同学</p>\n<p>2009011354 陈虹任<br />2011011318 徐子韵<br />2011011320 黄福林<br />2012010770 潘寅旭<br />2012011289 姚宇轩<br />2012011304 陈立康<br />2012011398 戚京翔<br />2012012407 邵成<br />2013011315 陈璞<br />2013011329 王邈<br />2013011333 王伟任<br /><br />2013011421 吴孟轩<br />2013011432 黄金帆<br />2013011433 张承佳楠<br />2013011434 王啸宇<br />2014011367 王奥丞</p>\n</div>", "anon": "no", "subject": "陈渝班-2016春季-第15讲 课堂思考题回答", "uid": "i76z9sx78G8", "created": "2016-04-21T15:41:53Z"}, {"content": "<p></p>\n<h1>2016春季-第15讲 课堂思考题回答-陈渝班</h1>\n<div>\n<p>请陈渝班的同学把“第十五讲 处理机调度”中指定小题的回答结果写在此贴中对应题目后面。</p>\n<p> </p>\n<p><a href=\"https://github.com/chyyuu/os_course_spoc_exercises/blob/master/all/06-1-spoc-discussion.md#小组练习与思考题\" target=\"_blank\">https://github.com/chyyuu/os_course_spoc_exercises/blob/master/all/06-1-spoc-discussion.md#小组练习与思考题</a></p>\n<p> </p>\n<p>第15讲的回答的截止时间是明天&#xff08;20160419&#xff09;晚20点前。<br /><br />要求&#xff1a;</p>\n<p>有8个“小组练习与思考题”&#xff0c;最多二个人一组&#xff0c;也可以独立回答。依据小组成员学号中最小学号除8后的余数&#xff0c;完成与余数&#43;1相同的题目。</p>\n<p> </p>\n<p><a href=\"https://github.com/chyyuu/os_course_spoc_exercises/blob/master/all/06-1-spoc-discussion.md#小组练习与思考题\" target=\"_blank\">https://github.com/chyyuu/os_course_spoc_exercises/blob/master/all/06-1-spoc-discussion.md#小组练习与思考题</a></p>\n<p> </p>\n<p>(1)理解并实现FIFO调度算法<br />(2)理解并实现SJF调度算法<br />(3)理解并实现RR调度算法<br />(4)理解并实现MLFQ调度算法<br />(5)理解并实现stride调度算法<br />(6)理解并实现EDF实时调度算法<br />(7)理解并实现RM实时调度算法<br />(8)理解并实现优先级反置方法</p>\n<p> </p>\n<p>注意&#xff0c;会检查完成情况&#xff0c;没有正确完成的同学算没有提交&#xff0c;尽量都放在github上&#xff0c;不要用网盘上传&#xff0c;有时候打不开。</p>\n<p>优胜者&#xff1a;</p>\n<p>杨志灿 2013011377 <br />邓志杰 2013011359<br />郑玉昆 2011011384<br />茹逸中 2013011375</p>\n<p>何晓楠 2013011361<br />游宇铭 2013011386</p>\n<p>陈昺弘 2013011380 </p>\n<p>马坚鑫 2013011384 </p>\n<p>未完成的同学</p>\n<p>2009011354 陈虹任<br />2011011318 徐子韵<br />2011011320 黄福林<br />2012010770 潘寅旭<br />2012011289 姚宇轩<br />2012011304 陈立康<br />2012011398 戚京翔<br />2012012407 邵成<br />2013011315 陈璞<br />2013011329 王邈<br />2013011333 王伟任<br />2013011335 何小豪<br />2013011421 吴孟轩<br />2013011432 黄金帆<br />2013011433 张承佳楠<br />2013011434 王啸宇<br />2014011367 王奥丞</p>\n</div>", "anon": "no", "subject": "陈渝班-2016春季-第15讲 课堂思考题回答", "uid": "i76z9sx78G8", "created": "2016-04-20T06:44:25Z"}, {"content": "<p></p>\n<h1>2016春季-第15讲 课堂思考题回答-陈渝班</h1>\n<div>\n<p>请陈渝班的同学把“第十五讲 处理机调度”中指定小题的回答结果写在此贴中对应题目后面。</p>\n<p> </p>\n<p><a href=\"https://github.com/chyyuu/os_course_spoc_exercises/blob/master/all/06-1-spoc-discussion.md#小组练习与思考题\" target=\"_blank\">https://github.com/chyyuu/os_course_spoc_exercises/blob/master/all/06-1-spoc-discussion.md#小组练习与思考题</a></p>\n<p> </p>\n<p>第15讲的回答的截止时间是明天&#xff08;20160419&#xff09;晚20点前。<br /><br />要求&#xff1a;</p>\n<p>有8个“小组练习与思考题”&#xff0c;最多二个人一组&#xff0c;也可以独立回答。依据小组成员学号中最小学号除8后的余数&#xff0c;完成与余数&#43;1相同的题目。</p>\n<p> </p>\n<p><a href=\"https://github.com/chyyuu/os_course_spoc_exercises/blob/master/all/06-1-spoc-discussion.md#小组练习与思考题\" target=\"_blank\">https://github.com/chyyuu/os_course_spoc_exercises/blob/master/all/06-1-spoc-discussion.md#小组练习与思考题</a></p>\n<p> </p>\n<p>(1)理解并实现FIFO调度算法<br />(2)理解并实现SJF调度算法<br />(3)理解并实现RR调度算法<br />(4)理解并实现MLFQ调度算法<br />(5)理解并实现stride调度算法<br />(6)理解并实现EDF实时调度算法<br />(7)理解并实现RM实时调度算法<br />(8)理解并实现优先级反置方法</p>\n<p> </p>\n<p>注意&#xff0c;会检查完成情况&#xff0c;没有正确完成的同学算没有提交&#xff0c;尽量都放在github上&#xff0c;不要用网盘上传&#xff0c;有时候打不开。</p>\n<p>优胜者&#xff1a;</p>\n<p>杨志灿 2013011377 <br />邓志杰 2013011359<br />郑玉昆 2011011384<br />茹逸中 2013011375</p>\n<p>何晓楠 2013011361<br />游宇铭 2013011386</p>\n<p>陈昺弘 2013011380 </p>\n<p>马坚鑫 2013011384 </p>\n</div>", "anon": "no", "subject": "陈渝班-2016春季-第15讲 课堂思考题回答", "uid": "i76z9sx78G8", "created": "2016-04-20T06:42:38Z"}, {"content": "<p></p>\n<h1>2016春季-第15讲 课堂思考题回答-陈渝班</h1>\n<div>\n<p>请陈渝班的同学把“第十五讲 处理机调度”中指定小题的回答结果写在此贴中对应题目后面。</p>\n<p> </p>\n<p><a href=\"https://github.com/chyyuu/os_course_spoc_exercises/blob/master/all/06-1-spoc-discussion.md#小组练习与思考题\" target=\"_blank\">https://github.com/chyyuu/os_course_spoc_exercises/blob/master/all/06-1-spoc-discussion.md#小组练习与思考题</a></p>\n<p> </p>\n<p>第15讲的回答的截止时间是明天&#xff08;20160419&#xff09;晚20点前。<br /><br />要求&#xff1a;</p>\n<p>有8个“小组练习与思考题”&#xff0c;最多二个人一组&#xff0c;也可以独立回答。依据小组成员学号中最小学号除8后的余数&#xff0c;完成与余数&#43;1相同的题目。</p>\n<p> </p>\n<p><a href=\"https://github.com/chyyuu/os_course_spoc_exercises/blob/master/all/06-1-spoc-discussion.md#小组练习与思考题\" target=\"_blank\">https://github.com/chyyuu/os_course_spoc_exercises/blob/master/all/06-1-spoc-discussion.md#小组练习与思考题</a></p>\n<p> </p>\n<p>(1)理解并实现FIFO调度算法<br />(2)理解并实现SJF调度算法<br />(3)理解并实现RR调度算法<br />(4)理解并实现MLFQ调度算法<br />(5)理解并实现stride调度算法<br />(6)理解并实现EDF实时调度算法<br />(7)理解并实现RM实时调度算法<br />(8)理解并实现优先级反置方法</p>\n<p> </p>\n<p>注意&#xff0c;会检查完成情况&#xff0c;没有正确完成的同学算没有提交&#xff0c;尽量都放在github上&#xff0c;不要用网盘上传&#xff0c;有时候打不开。</p>\n<p>优胜者&#xff1a;</p>\n<p>杨志灿 2013011377 <br />邓志杰 2013011359<br />郑玉昆 2011011384<br />茹逸中 2013011375</p>\n</div>", "anon": "no", "subject": "陈渝班-2016春季-第15讲 课堂思考题回答", "uid": "i76z9sx78G8", "created": "2016-04-18T08:04:10Z"}, {"content": "<p></p>\n<h1>2016春季-第15讲 课堂思考题回答-陈渝班</h1>\n<div>\n<p>请陈渝班的同学把“第十五讲 处理机调度”中指定小题的回答结果写在此贴中对应题目后面。</p>\n<p> </p>\n<p><a href=\"https://github.com/chyyuu/os_course_spoc_exercises/blob/master/all/06-1-spoc-discussion.md#小组练习与思考题\" target=\"_blank\">https://github.com/chyyuu/os_course_spoc_exercises/blob/master/all/06-1-spoc-discussion.md#小组练习与思考题</a></p>\n<p> </p>\n<p>第15讲的回答的截止时间是明天&#xff08;20160419&#xff09;晚20点前。<br /><br />要求&#xff1a;</p>\n<p>有8个“小组练习与思考题”&#xff0c;最多二个人一组&#xff0c;也可以独立回答。依据小组成员学号中最小学号除8后的余数&#xff0c;完成与余数&#43;1相同的题目。</p>\n<p> </p>\n<p><a href=\"https://github.com/chyyuu/os_course_spoc_exercises/blob/master/all/06-1-spoc-discussion.md#小组练习与思考题\" target=\"_blank\">https://github.com/chyyuu/os_course_spoc_exercises/blob/master/all/06-1-spoc-discussion.md#小组练习与思考题</a></p>\n<p> </p>\n<p>(1)理解并实现FIFO调度算法<br />(2)理解并实现SJF调度算法<br />(3)理解并实现RR调度算法<br />(4)理解并实现MLFQ调度算法<br />(5)理解并实现stride调度算法<br />(6)理解并实现EDF实时调度算法<br />(7)理解并实现RM实时调度算法<br />(8)理解并实现优先级反置方法</p>\n<p> </p>\n<p>注意&#xff0c;会检查完成情况的&#xff0c;尽量都放在github上&#xff0c;不要用网盘上传&#xff0c;有时候打不开。</p>\n<p>优胜者&#xff1a;</p>\n<p>杨志灿 2013011377 <br />邓志杰 2013011359<br />郑玉昆 2011011384<br />茹逸中 2013011375</p>\n</div>", "anon": "no", "subject": "陈渝班-2016春季-第15讲 课堂思考题回答", "uid": "i76z9sx78G8", "created": "2016-04-18T08:03:41Z"}, {"content": "<p></p>\n<h1>2016春季-第15讲 课堂思考题回答-陈渝班</h1>\n<div>\n<p>请陈渝班的同学把“第十五讲 处理机调度”中指定小题的回答结果写在此贴中对应题目后面。</p>\n<p> </p>\n<p><a href=\"https://github.com/chyyuu/os_course_spoc_exercises/blob/master/all/06-1-spoc-discussion.md#小组练习与思考题\" target=\"_blank\">https://github.com/chyyuu/os_course_spoc_exercises/blob/master/all/06-1-spoc-discussion.md#小组练习与思考题</a></p>\n<p> </p>\n<p>第15讲的回答的截止时间是明天&#xff08;20160419&#xff09;晚20点前。<br /><br />要求&#xff1a;</p>\n<p>有8个“小组练习与思考题”&#xff0c;最多二个人一组&#xff0c;也可以独立回答。依据小组成员学号中最小学号除8后的余数&#xff0c;完成与余数&#43;1相同的题目。</p>\n<p> </p>\n<p><a href=\"https://github.com/chyyuu/os_course_spoc_exercises/blob/master/all/06-1-spoc-discussion.md#小组练习与思考题\" target=\"_blank\">https://github.com/chyyuu/os_course_spoc_exercises/blob/master/all/06-1-spoc-discussion.md#小组练习与思考题</a></p>\n<p> </p>\n<p>(1)理解并实现FIFO调度算法<br />(2)理解并实现SJF调度算法<br />(3)理解并实现RR调度算法<br />(4)理解并实现MLFQ调度算法<br />(5)理解并实现stride调度算法<br />(6)理解并实现EDF实时调度算法<br />(7)理解并实现RM实时调度算法<br />(8)理解并实现优先级反置方法</p>\n<p> </p>\n<p>优胜者&#xff1a;</p>\n<p></p>\n</div>", "anon": "no", "subject": "陈渝班-2016春季-第15讲 课堂思考题回答", "uid": "hcrrjuyequh4bt", "created": "2016-04-18T01:12:53Z"}, {"content": "<p></p>\n<h1>2016春季-第15讲 课堂思考题回答-陈渝班</h1>\n<div>\n<p>请陈渝班的同学把“第十五讲 处理机调度”中指定小题的回答结果写在此贴中对应题目后面。</p>\n<p> </p>\n<p><a href=\"https://github.com/chyyuu/os_course_spoc_exercises/blob/master/all/06-1-spoc-discussion.md#小组练习与思考题\" target=\"_blank\">https://github.com/chyyuu/os_course_spoc_exercises/blob/master/all/06-1-spoc-discussion.md#小组练习与思考题</a></p>\n<p> </p>\n<p>第15讲的回答的截止时间是明天&#xff08;20160419&#xff09;晚20点前。<br /><br />要求&#xff1a;</p>\n<p>有8个“小组练习与思考题”&#xff0c;最多二个人一组&#xff0c;也可以独立回答。依据小组成员学号中最小学号除8后的余数&#43;1&#xff0c;完成与余数&#43;1相同的题目。</p>\n<p> </p>\n<p><a href=\"https://github.com/chyyuu/os_course_spoc_exercises/blob/master/all/06-1-spoc-discussion.md#小组练习与思考题\" target=\"_blank\">https://github.com/chyyuu/os_course_spoc_exercises/blob/master/all/06-1-spoc-discussion.md#小组练习与思考题</a></p>\n<p> </p>\n<p>(1)理解并实现FIFO调度算法<br />(2)理解并实现SJF调度算法<br />(3)理解并实现RR调度算法<br />(4)理解并实现MLFQ调度算法<br />(5)理解并实现stride调度算法<br />(6)理解并实现EDF实时调度算法<br />(7)理解并实现RM实时调度算法<br />(8)理解并实现优先级反置方法</p>\n<p> </p>\n<p>优胜者&#xff1a;</p>\n<p></p>\n</div>", "anon": "no", "subject": "陈渝班-2016春季-第15讲 课堂思考题回答", "uid": "hcrrjuyequh4bt", "created": "2016-04-18T01:12:28Z"}, {"content": "<p></p><h1>2016春季-第15讲 课堂思考题回答-陈渝班</h1>\n<div>\n<p>请陈渝班的同学把“第十五讲 处理机调度”中指定小题的回答结果写在此贴中对应题目后面。</p>\n<p> </p>\n<p><a href=\"https://github.com/chyyuu/os_course_spoc_exercises/blob/master/all/06-1-spoc-discussion.md#小组练习与思考题\" target=\"_blank\">https://github.com/chyyuu/os_course_spoc_exercises/blob/master/all/06-1-spoc-discussion.md#小组练习与思考题</a></p>\n<p> </p>\n<p>第15讲的回答的截止时间是明天&#xff08;20160419&#xff09;晚20点前。<br /><br />要求&#xff1a;</p>\n<p>有8个“小组练习与思考题”&#xff0c;最多二个人一组&#xff0c;也可以独立回答。依据小组成员学号中最小学号除2后的余数&#xff0c;完成与余数相同的题目。</p>\n<p> </p>\n<p><a href=\"https://github.com/chyyuu/os_course_spoc_exercises/blob/master/all/06-1-spoc-discussion.md#小组练习与思考题\" target=\"_blank\">https://github.com/chyyuu/os_course_spoc_exercises/blob/master/all/06-1-spoc-discussion.md#小组练习与思考题</a></p>\n<p> </p>\n<p>(1)理解并实现FIFO调度算法<br />(2)理解并实现SJF调度算法<br />(3)理解并实现RR调度算法<br />(4)理解并实现MLFQ调度算法<br />(5)理解并实现stride调度算法<br />(6)理解并实现EDF实时调度算法<br />(7)理解并实现RM实时调度算法<br />(8)理解并实现优先级反置方法</p>\n<p> </p>\n<p>优胜者&#xff1a;</p>\n<p></p>\n</div>", "anon": "no", "subject": "陈渝班-2016春季-第15讲 课堂思考题回答", "uid": "hcrrjuyequh4bt", "created": "2016-04-18T01:08:19Z"}]}, "error": null}