{"aid": "inkg6ix23kh7df", "result": {"folders": ["big_proj", "通知", "课程设计"], "unique_views": 14, "request_instructor_me": false, "change_log": [{"data": "inj1nvx77a723w", "anon": "no", "when": "2016-04-27T15:56:38Z", "uid": "hdjonbiyfs62ie", "type": "create"}, {"data": "injmhkrbl6x4yu", "anon": "no", "when": "2016-04-28T01:39:36Z", "uid": "hdjonbiyfs62ie", "type": "update"}, {"to": "inj1nvx33hm23v", "anon": "no", "when": "2016-04-28T01:40:51Z", "uid": "hdjonbiyfs62ie", "type": "followup"}, {"to": "inj1nvx33hm23v", "anon": "no", "when": "2016-04-28T02:26:22Z", "uid": "iem550jbpyn515", "type": "feedback"}, {"to": "inj1nvx33hm23v", "anon": "no", "when": "2016-04-28T04:25:19Z", "uid": "hdjonbiyfs62ie", "type": "feedback"}, {"to": "inj1nvx33hm23v", "anon": "no", "when": "2016-04-28T04:34:30Z", "uid": "iem550jbpyn515", "type": "feedback"}, {"to": "inj1nvx33hm23v", "anon": "no", "when": "2016-04-28T07:10:03Z", "uid": "hdjonbiyfs62ie", "type": "feedback"}], "upvote_ids": [], "id": "inj1nvx33hm23v", "bookmarked": 2, "no_answer_followup": 0, "i_edits": [], "is_bookmarked": false, "children": [{"folders": [], "updated": "2016-04-28T01:40:51Z", "no_upvotes": 0, "uid": "hdjonbiyfs62ie", "created": "2016-04-28T01:40:51Z", "type": "followup", "no_answer": 0, "id": "injmj6r24pz5tv", "anon": "no", "bucket_name": "Today", "config": {}, "bucket_order": 2, "data": null, "children": [{"folders": [], "updated": "2016-04-28T02:26:22Z", "uid": "iem550jbpyn515", "created": "2016-04-28T02:26:22Z", "type": "feedback", "id": "injo5plum152x2", "anon": "no", "bucket_name": "Today", "config": {}, "bucket_order": 2, "data": null, "children": [], "subject": "<p>向老师&#xff0c;我们组遇到紧急bug了……</p>\n<p>如果可以的话&#xff0c;不知道老师周五有没有时间能单独讨论一下 拜托了</p>"}, {"folders": [], "updated": "2016-04-28T04:25:19Z", "uid": "hdjonbiyfs62ie", "created": "2016-04-28T04:25:19Z", "type": "feedback", "id": "injseoo0l2j1rc", "anon": "no", "bucket_name": "Today", "config": {}, "bucket_order": 2, "data": null, "children": [], "subject": "<p>我周五或周六上午9点可以与你们在东主楼9区410室讨论。哪个时间方便&#xff1f;</p>"}, {"folders": [], "updated": "2016-04-28T04:34:30Z", "uid": "iem550jbpyn515", "created": "2016-04-28T04:34:30Z", "type": "feedback", "id": "injsqhuztms6ic", "anon": "no", "bucket_name": "Today", "config": {}, "bucket_order": 2, "data": null, "children": [], "subject": "<p>那就周五上午9点吧&#xff0c;谢谢向老师&#xff1a;&#xff09;</p>"}, {"folders": [], "updated": "2016-04-28T07:10:03Z", "uid": "hdjonbiyfs62ie", "created": "2016-04-28T07:10:03Z", "type": "feedback", "id": "injyajj78wp3nb", "anon": "no", "bucket_name": "Today", "config": {}, "bucket_order": 2, "data": null, "children": [], "subject": "<p>好的。</p>"}], "subject": "<p>不好意思。由于时间协调问题&#xff0c;最后落实下来的讨论时间是周六上午10点。</p>"}], "nr": 841, "bucket_order": 2, "config": {"feed_groups": "课程设计_i5j09fnsl7k5x0"}, "status": "active", "tags": ["big_proj", "instructor-note", "课程设计", "通知"], "num_favorites": 0, "bucket_name": "Today", "q_edits": [], "data": {"embed_links": []}, "request_instructor": 0, "created": "2016-04-27T15:56:38Z", "is_tag_good": false, "type": "note", "s_edits": [], "my_favorite": false, "default_anonymity": "no", "t": 1461857449286, "tag_good": [], "tag_good_arr": [], "history": [{"content": "<p>时间&#xff1a;2016.04.30&#xff08;周六&#xff09; 上午10:00~12:00<br />地点&#xff1a;东主楼9区410室<br />内容&#xff1a;各组汇报各自的进展&#xff0c;并进行讨论</p>\n<p></p>\n<p>由于很难协调到大家都方便的时间&#xff0c;最后只好安排在相对方便的这个时间了。</p>\n<p>希望&#xff08;不是“要求”了&#xff09;每个人都参加&#xff0c;而不是只来一个代表。</p>\n<p></p>\n<p>请相互转告</p>", "anon": "no", "subject": "通知&#xff1a;请参加课程设计交流", "uid": "hdjonbiyfs62ie", "created": "2016-04-28T01:39:36Z"}, {"content": "<p>时间&#xff1a;2016.04.30&#xff08;周六&#xff09; 下午14:00~18:00<br />地点&#xff1a;东主楼9区410室<br />内容&#xff1a;各组汇报各自的进展&#xff0c;并进行讨论</p>\n<p></p>\n<p>要求每个人都参加&#xff0c;而不是只来一个代表</p>\n<p>请相互转告</p>", "anon": "no", "subject": "通知&#xff1a;请参加课程设计交流", "uid": "hdjonbiyfs62ie", "created": "2016-04-27T15:56:38Z"}]}, "error": null}