{"aid": "iztz8mmq1fxp7", "result": {"status": "active", "unique_views": 85, "request_instructor_me": false, "change_log": [{"type": "create", "anon": "no", "when": "2017-02-15T12:54:12Z", "data": "iz6ylpbajqv39c", "uid": "iu9y80pnSRp"}, {"to": "iz6ylpb7tzl39b", "anon": "no", "when": "2017-03-03T06:51:19Z", "type": "followup", "uid": "ierwkwbinsj2t8"}], "upvote_ids": [], "id": "iz6ylpb7tzl39b", "bookmarked": 4, "no_answer": 1, "i_edits": [], "is_bookmarked": false, "children": [{"folders": [], "updated": "2017-03-03T06:51:19Z", "no_upvotes": 0, "uid": "ierwkwbinsj2t8", "created": "2017-03-03T06:51:19Z", "type": "followup", "no_answer": 0, "id": "iztgoo2igcp7c", "anon": "no", "bucket_name": "Today", "config": {}, "bucket_order": 2, "data": null, "children": [], "subject": "<p>可以尝试用<tt>file</tt>命令加载文件&#xff0c;如果是进入了kernel就加载kernel image&#xff0c;否则需要加载bootloader。</p>\n<p></p>"}], "nr": 966, "bucket_order": 2, "type": "question", "folders": ["lab1"], "no_answer_followup": 0, "num_favorites": 0, "bucket_name": "Today", "q_edits": [], "data": {"embed_links": []}, "request_instructor": 0, "tags": ["lab1", "student", "unanswered"], "created": "2017-02-15T12:54:12Z", "is_tag_good": false, "config": {}, "s_edits": [], "my_favorite": false, "default_anonymity": "no", "t": 1488555043730, "tag_good": [], "tag_good_arr": [], "history": [{"content": "<p>老师你好&#xff0c;我想问问这个问题出现的原因和解决办法。</p>\n<p>在gdb和qemu连接后&#xff0c;以set arch 8086、target remote&#xff1a;1234、si、b*0x7c00、continue&#xff0c;初始化后&#xff0c;输入step进行单步调试会出现 cannot find bounds of current function这个问题。在网上查找答案无果&#xff0c;只好来Piazza请教。</p>\n<p>谢谢&#xff01;&#xff01;&#xff01;</p>", "anon": "no", "created": "2017-02-15T12:54:12Z", "uid": "iu9y80pnSRp", "subject": "cannot find bounds of current function?"}]}, "error": null}