{"error": null, "result": {"nr": 286, "upvote_ids": [], "change_log": [{"type": "create", "when": "2015-04-11T18:11:33Z", "uid": "i6uayl3vEOz", "data": "i8dc9z1hz2o7j3", "anon": "no"}, {"uid": "i6t1byqz5dE", "to": "i8dc9z0i21p7j2", "when": "2015-04-11T18:13:49Z", "anon": "no", "data": "i8dccw4hdgpnr", "type": "s_answer"}, {"uid": "i6ucxgbeel362h", "to": "i8dc9z0i21p7j2", "when": "2015-04-12T18:55:00Z", "anon": "no", "data": "i8et9pmm2q334l", "type": "i_answer"}, {"type": "followup", "to": "i8dc9z0i21p7j2", "when": "2015-04-13T02:05:08Z", "uid": "i6roqnlkmtw", "anon": "no"}, {"type": "followup", "to": "i8dc9z0i21p7j2", "when": "2015-04-13T02:20:09Z", "uid": "hcrrjuyequh4bt", "anon": "no"}], "q_edits": [], "i_edits": [], "unique_views": 55, "bookmarked": 7, "config": {}, "history": [{"subject": "对一个不能写的页面进行写操作&#xff0c;会引发什么异常&#xff1f;", "content": "<p>如题</p>", "created": "2015-04-11T18:11:33Z", "uid": "i6uayl3vEOz", "anon": "no"}], "data": {"embed_links": []}, "request_instructor_me": false, "folders": ["exam"], "type": "question", "tag_good": [], "no_answer": 0, "created": "2015-04-11T18:11:33Z", "t": 1433500304097, "id": "i8dc9z0i21p7j2", "status": "active", "tag_good_arr": [], "default_anonymity": "no", "my_favorite": false, "bucket_order": 2, "is_bookmarked": false, "is_tag_good": false, "bucket_name": "Today", "no_answer_followup": 0, "children": [{"folders": [], "bucket_order": 2, "config": {}, "history": [{"subject": "", "content": "<p>应该是 GPF general protection fault 吧</p>", "created": "2015-04-11T18:13:49Z", "uid": "i6t1byqz5dE", "anon": "no"}], "data": {"embed_links": []}, "bucket_name": "Today", "is_tag_endorse": false, "children": [], "tag_endorse": [], "tag_endorse_arr": [], "created": "2015-04-11T18:13:49Z", "id": "i8dccw3fntvnq", "type": "s_answer"}, {"folders": [], "bucket_order": 2, "config": {}, "history": [{"subject": "", "content": "<p>http://en.wikipedia.org/wiki/General_protection_fault</p>", "created": "2015-04-12T18:55:00Z", "uid": "i6ucxgbeel362h", "anon": "no"}], "data": {"embed_links": []}, "bucket_name": "Today", "is_tag_endorse": false, "children": [], "tag_endorse": [], "tag_endorse_arr": [], "created": "2015-04-12T18:55:00Z", "id": "i8et9pmkcq834k", "type": "i_answer"}, {"no_upvotes": 0, "uid": "i6roqnlkmtw", "bucket_name": "Last week", "bucket_order": 5, "updated": "2015-04-13T02:05:08Z", "config": {}, "anon": "no", "data": {"embed_links": null}, "folders": [], "subject": "<p>在ucore中</p>\n<p>General_protection_fault在trap.c中好像没有对应的处理代码啊</p>\n<p>是都当成page fault统一处理了是吗&#xff1f;</p>", "children": [], "type": "followup", "no_answer": 0, "created": "2015-04-13T02:05:08Z", "id": "i8f8muxinld1ma"}, {"no_upvotes": 0, "uid": "hcrrjuyequh4bt", "bucket_name": "Last week", "bucket_order": 5, "updated": "2015-04-13T02:20:09Z", "config": {}, "anon": "no", "data": {"embed_links": null}, "folders": [], "subject": "<p>对于80386而言&#xff0c;这里首先需要明确&#xff0c;如果设定“不可写”或&#34;只读&#34;&#xff0c;而且需要了解CPU的保护检查的流程。</p>\n<p>考虑到80386有段和页两种保护检查机制&#xff0c;所以在不同设定下&#xff0c;会产生不同的异常。</p>\n<p>请同学再思考一下。</p>", "children": [], "type": "followup", "no_answer": 0, "created": "2015-04-13T02:20:09Z", "id": "i8f966529zk7n3"}], "request_instructor": 0, "tags": ["exam", "student"], "s_edits": [], "num_favorites": 0}, "aid": "iajh2hnlt1h786"}