{"error": null, "result": {"nr": 441, "upvote_ids": [], "change_log": [{"type": "create", "when": "2015-05-18T13:49:26Z", "uid": "i6z6k9yt7b77nz", "data": "i9ty7ev8yu41bd", "anon": "no"}, {"type": "followup", "to": "i9ty7ethldi1bc", "when": "2015-05-18T13:57:50Z", "uid": "i7bfq2txxyw689", "anon": "no"}, {"uid": "i6t1byqz5dE", "to": "i9ty7ethldi1bc", "when": "2015-05-18T16:37:52Z", "anon": "no", "data": "i9u480x9mnu389", "type": "s_answer"}], "q_edits": [], "i_edits": [], "unique_views": 59, "bookmarked": 4, "config": {}, "history": [{"subject": "VirtualBox 怎么扩大虚拟磁盘容量&#xff1f;", "content": "<p>VirtualBox最开始的时候这个有8G的容量&#xff0c;现在有点不够用了&#xff0c;如何才能扩展现有的这个虚拟磁盘呢&#xff1f;</p>\n<p></p>\n<p>我在网上找了一些方法&#xff0c;但是都不好使&#xff0c;有人有这方面的经验吗&#xff1f;</p>", "created": "2015-05-18T13:49:26Z", "uid": "i6z6k9yt7b77nz", "anon": "no"}], "data": {"embed_links": []}, "request_instructor_me": false, "folders": ["lab0"], "type": "question", "tag_good": [], "no_answer": 0, "created": "2015-05-18T13:49:26Z", "t": 1433500546171, "id": "i9ty7ethldi1bc", "status": "active", "tag_good_arr": [], "default_anonymity": "no", "my_favorite": false, "bucket_order": 2, "is_bookmarked": false, "is_tag_good": false, "bucket_name": "Today", "no_answer_followup": 0, "children": [{"no_upvotes": 0, "uid": "i7bfq2txxyw689", "bucket_name": "Yesterday", "bucket_order": 3, "updated": "2015-05-18T13:57:50Z", "config": {}, "d-bucket": "Yesterday", "data": {"embed_links": null}, "anon": "no", "folders": [], "subject": "<p>把之前make生成的都 “make clean”吧~</p>", "children": [], "type": "followup", "no_answer": 0, "created": "2015-05-18T13:57:50Z", "id": "i9tyi7v4jd43pn"}, {"folders": [], "bucket_order": 2, "config": {}, "history": [{"subject": "", "content": "<p><a href=\"http://www.betaflare.com/enlarge-virtual-machine-disk-in-virtualbox.html\">http://www.betaflare.com/enlarge-virtual-machine-disk-in-virtualbox.html</a> 亲测可用</p>", "created": "2015-05-18T16:37:52Z", "uid": "i6t1byqz5dE", "anon": "no"}], "data": {"embed_links": []}, "bucket_name": "Today", "is_tag_endorse": false, "children": [], "tag_endorse": [], "tag_endorse_arr": [], "created": "2015-05-18T16:37:52Z", "id": "i9u480x6bmm388", "type": "s_answer"}], "request_instructor": 0, "tags": ["lab0", "student"], "s_edits": [], "num_favorites": 0}, "aid": "iajh7ofv7s34h7"}